clean_architecture_basic_classes/__init__.py
clean_architecture_basic_classes/cli.py
clean_architecture_basic_classes/basic_domain/__init__.py
clean_architecture_basic_classes/basic_domain/basic_entity.py
clean_architecture_basic_classes/basic_domain/basic_value.py
clean_architecture_basic_classes/basic_domain/task_scheduler_port.py
clean_architecture_basic_classes/basic_domain/util.py
clean_architecture_basic_classes/basic_interactors/__init__.py
clean_architecture_basic_classes/basic_interactors/basic_delete.py
clean_architecture_basic_classes/basic_interactors/basic_get.py
clean_architecture_basic_classes/basic_interactors/basic_get_all.py
clean_architecture_basic_classes/basic_interactors/basic_post.py
clean_architecture_basic_classes/basic_interactors/basic_put.py
clean_architecture_basic_classes/basic_persist_adapter/__init__.py
clean_architecture_basic_classes/basic_persist_adapter/basic_persist_adapter.py
clean_architecture_basic_classes/basic_routes/__init__.py
clean_architecture_basic_classes/basic_routes/basic_routes.py
clean_architecture_basic_classes/basic_routes/exceptions.py
clean_architecture_basic_classes/basic_scheduler_adapter/__init__.py
clean_architecture_basic_classes/basic_scheduler_adapter/basic_scheduler_adapter.py
clean_architecture_basic_classes-0.1.3.dist-info/LICENSE
clean_architecture_basic_classes-0.1.3.dist-info/METADATA
clean_architecture_basic_classes-0.1.3.dist-info/WHEEL
clean_architecture_basic_classes-0.1.3.dist-info/entry_points.txt
clean_architecture_basic_classes-0.1.3.dist-info/top_level.txt
clean_architecture_basic_classes-0.1.3.dist-info/RECORD
