Metadata-Version: 2.1
Name: clean-architecture-basic-classes
Version: 0.1.3
Summary: Classes to implement a Clean Architecture Python Framework
Home-page: https://github.com/aberriel/clean_architecture_basic_classes
Author: Anselmo Lira (https://github.com/aberriel)
Author-email: anselmo.lira1@gmail.com
License: UNKNOWN
Keywords: clean_architecture_basic_classes
Platform: UNKNOWN
Classifier: Development Status :: 2 - Pre-Alpha
Classifier: Intended Audience :: Developers
Classifier: Natural Language :: English
Classifier: Programming Language :: Python :: 3.8
Requires-Python: >=3.8
License-File: LICENSE
Requires-Dist: marshmallow (==3.14.0)
Requires-Dist: bumpversion (==0.6.0)
